[
    {
        "id": "402-6135736-4529108",
        "uri": "https://sellercentral.amazon.in/orders-v3/order/402-6135736-4529108",
        "order": "Wed, 1 Mar, 2023, 7:44 pm IST",
        "shipment": "Thu, 2 Mar, 2023",
        "delivery": "Fri, 3 Mar, 2023",
        "status": "Delivered to buyer",
        "products": [
            {
                "name": "Angel Sales Women's Multi Color Bow Wedge Heel - FEMOF_19 (Multi Color, numeric_4)ASIN:  B0BRQRX696SKU:  MN-N5QI-9H00",
                "thumbnail": "https://m.media-amazon.com/images/I/31YwkleHGaL._SCLZZZZZZZ__SX55_.jpg",
                "uri": "https://www.amazon.in/gp/product/B0BRQRX696",
                "transaction": {
                    "listingPrice": "₹595.00",
                    "tax": "63.76",
                    "payment": "₹466.51",
                    "shipping": "-₹47.20"
                }
            }
        ],
        "customer": {
            "name": "Prachi",
            "address": "MUMBAI, MAHARASHTRA",
            "pincode": "400072"
        }
    },
    {
        "id": "408-7449763-5256367",
        "uri": "https://sellercentral.amazon.in/orders-v3/order/408-7449763-5256367",
        "order": "Thu, 2 Mar, 2023, 5:18 pm IST",
        "shipment": "Fri, 3 Mar, 2023",
        "delivery": "Mon, 6 Mar, 2023",
        "status": "Delivered to buyer",
        "products": [
            {
                "name": "Angel Sales Women's Eva Comfortable Wedges Chappal Sliper (Grey); Size: 9 - FEMOF_04ASIN:  B0BR7QNJ8BSKU:  FEMOF_004-GY/9",
                "thumbnail": "https://m.media-amazon.com/images/I/31M5uBtFTBL._SCLZZZZZZZ__SX55_.jpg",
                "uri": "https://www.amazon.in/gp/product/B0BR7QNJ8B",
                "transaction": {
                    "listingPrice": "₹655.00",
                    "tax": "70.18",
                    "payment": "₹505.54",
                    "shipping": "-₹84.96"
                }
            }
        ],
        "customer": {
            "name": "chitra",
            "address": "CHENNAI, TAMIL NADU",
            "pincode": "600122"
        }
    },
    {
        "id": "402-7893232-3855506",
        "uri": "https://sellercentral.amazon.in/orders-v3/order/402-7893232-3855506",
        "order": "Fri, 3 Mar, 2023, 12:29 am IST",
        "shipment": "Fri, 3 Mar, 2023",
        "delivery": "Tue, 7 Mar, 2023",
        "status": "Delivered to buyer",
        "products": [
            {
                "name": "Angel Sales Women's Eva Comfortable Sandal (Grey); Size: 6 - FEMOF_05ASIN:  B0BR7RP3HFSKU:  FEMOF_005-GY/6",
                "thumbnail": "https://m.media-amazon.com/images/I/41s60V4tUDL._SCLZZZZZZZ__SX55_.jpg",
                "uri": "https://www.amazon.in/gp/product/B0BR7RP3HF",
                "transaction": {
                    "listingPrice": "₹465.00",
                    "tax": "47.33",
                    "payment": "₹376.73",
                    "shipping": "-₹84.96"
                }
            }
        ],
        "customer": {
            "name": "Anjali",
            "address": "MUKUNDAPURAM, KERALA",
            "pincode": "680303"
        }
    },
    {
        "id": "405-1967359-5638725",
        "uri": "https://sellercentral.amazon.in/orders-v3/order/405-1967359-5638725",
        "order": "Fri, 3 Mar, 2023, 8:12 am IST",
        "shipment": "Fri, 3 Mar, 2023",
        "delivery": "Tue, 7 Mar, 2023",
        "status": "Delivered to buyer",
        "products": [
            {
                "name": "Angel Sales Women's Multi Color Bow Wedge Heel - FEMOF_19 (Multi Color, numeric_6)ASIN:  B0BRQR3P6CSKU:  US-C5PS-D9YK",
                "thumbnail": "https://m.media-amazon.com/images/I/31YwkleHGaL._SCLZZZZZZZ__SX55_.jpg",
                "uri": "https://www.amazon.in/gp/product/B0BRQR3P6C",
                "transaction": {
                    "listingPrice": "₹595.00",
                    "tax": "63.75",
                    "refund": "-₹555.02",
                    "payment": "₹466.52",
                    "shipping": "-₹60.18"
                }
            }
        ],
        "customer": {
            "name": "Divya",
            "address": "NEEMUCH, MADHYA PRADESH",
            "pincode": "458441"
        }
    },
    {
        "id": "408-4418290-0057911",
        "uri": "https://sellercentral.amazon.in/orders-v3/order/408-4418290-0057911",
        "order": "Fri, 3 Mar, 2023, 12:21 pm IST",
        "shipment": "Fri, 3 Mar, 2023",
        "delivery": "Mon, 6 Mar, 2023",
        "status": "Delivered to buyer",
        "products": [
            {
                "name": "Angel Sales Women's Multi Color Bow Wedge Heel - FEMOF_19 (Multi Color, numeric_8)ASIN:  B0BRQT2ZJTSKU:  AA-PC1E-AFK2",
                "thumbnail": "https://m.media-amazon.com/images/I/31YwkleHGaL._SCLZZZZZZZ__SX55_.jpg",
                "uri": "https://www.amazon.in/gp/product/B0BRQT2ZJT",
                "transaction": {
                    "listingPrice": "₹595.00",
                    "tax": "63.75",
                    "payment": "₹466.52",
                    "shipping": "-₹84.96"
                }
            }
        ],
        "customer": {
            "name": "ASHOK",
            "address": "BENGALURU, KARNATAKA",
            "pincode": "560078"
        }
    },
    {
        "id": "405-7479368-3812333",
        "uri": "https://sellercentral.amazon.in/orders-v3/order/405-7479368-3812333",
        "order": "Fri, 3 Mar, 2023, 2:58 pm IST",
        "shipment": "Sat, 4 Mar, 2023",
        "delivery": "Tue, 7 Mar, 2023",
        "status": "Delivered to buyer",
        "products": [
            {
                "name": "Angel Sales Women's Multi Color Bow Wedge Heel - FEMOF_19 (Multi Color, numeric_5)ASIN:  B0BRQRCGB8SKU:  MS-GG5E-KZ1Y",
                "thumbnail": "https://m.media-amazon.com/images/I/31YwkleHGaL._SCLZZZZZZZ__SX55_.jpg",
                "uri": "https://www.amazon.in/gp/product/B0BRQRCGB8",
                "transaction": {
                    "listingPrice": "₹595.00",
                    "tax": "63.75",
                    "refund": "-₹555.02",
                    "payment": "₹466.52",
                    "shipping": "-₹84.96"
                }
            }
        ],
        "customer": {
            "name": "Tania",
            "address": "BENGALURU, KARNATAKA",
            "pincode": "560064"
        }
    },
    {
        "id": "407-0128263-0173101",
        "uri": "https://sellercentral.amazon.in/orders-v3/order/407-0128263-0173101",
        "order": "Sat, 4 Mar, 2023, 12:48 am IST",
        "shipment": "Sat, 4 Mar, 2023",
        "delivery": "Sun, 5 Mar, 2023",
        "status": "Delivered to buyer",
        "products": [
            {
                "name": "Angel Sales Women's Multi Color Bow Wedge Heel - FEMOF_19 (Multi Color, numeric_4)ASIN:  B0BRQRX696SKU:  MN-N5QI-9H00",
                "thumbnail": "https://m.media-amazon.com/images/I/31YwkleHGaL._SCLZZZZZZZ__SX55_.jpg",
                "uri": "https://www.amazon.in/gp/product/B0BRQRX696",
                "transaction": {
                    "listingPrice": "₹595.00",
                    "tax": "63.76",
                    "payment": "₹466.51",
                    "shipping": "-₹47.20"
                }
            }
        ],
        "customer": {
            "name": "Monica",
            "address": "THANE, MAHARASHTRA",
            "pincode": "400615"
        }
    },
    {
        "id": "406-8647675-2577917",
        "uri": "https://sellercentral.amazon.in/orders-v3/order/406-8647675-2577917",
        "order": "Sat, 4 Mar, 2023, 8:42 pm IST",
        "shipment": "Sun, 5 Mar, 2023",
        "delivery": "Thu, 9 Mar, 2023",
        "status": "Delivered to buyer",
        "products": [
            {
                "name": "Angel Sales Women's Multi Color Bow Wedge Heel - FEMOF_19 (Multi Color, numeric_6)ASIN:  B0BRQR3P6CSKU:  US-C5PS-D9YK",
                "thumbnail": "https://m.media-amazon.com/images/I/31YwkleHGaL._SCLZZZZZZZ__SX55_.jpg",
                "uri": "https://www.amazon.in/gp/product/B0BRQR3P6C",
                "transaction": {
                    "listingPrice": "₹595.00",
                    "tax": "63.75",
                    "payment": "₹466.52",
                    "shipping": "-₹84.96"
                }
            }
        ],
        "customer": {
            "name": "Parul",
            "address": "GURUGRAM, HARYANA",
            "pincode": "122003"
        }
    },
    {
        "id": "402-4380411-4809935",
        "uri": "https://sellercentral.amazon.in/orders-v3/order/402-4380411-4809935",
        "order": "Sun, 5 Mar, 2023, 4:19 pm IST",
        "shipment": "Mon, 6 Mar, 2023",
        "delivery": "Fri, 10 Mar, 2023",
        "status": "Delivered to buyer",
        "products": [
            {
                "name": "Angel Sales Women's Multi Color Bow Wedge Heel - FEMOF_19 (Multi Color, numeric_5)ASIN:  B0BRQRCGB8SKU:  MS-GG5E-KZ1Y",
                "thumbnail": "https://m.media-amazon.com/images/I/31YwkleHGaL._SCLZZZZZZZ__SX55_.jpg",
                "uri": "https://www.amazon.in/gp/product/B0BRQRCGB8",
                "transaction": {
                    "listingPrice": "₹595.00",
                    "tax": "63.75",
                    "refund": "-₹466.52",
                    "payment": "₹466.52",
                    "shipping": "-₹84.96"
                }
            }
        ],
        "customer": {
            "name": "Rakhi",
            "address": "LUCKNOW, UTTAR PRADESH",
            "pincode": "226021"
        }
    },
    {
        "id": "407-6187466-6761103",
        "uri": "https://sellercentral.amazon.in/orders-v3/order/407-6187466-6761103",
        "order": "Sun, 5 Mar, 2023, 7:30 pm IST",
        "shipment": "Mon, 6 Mar, 2023",
        "delivery": "Thu, 9 Mar, 2023",
        "status": "Delivered to buyer",
        "products": [
            {
                "name": "Angel Sales Women's Multi Color Bow Wedge Heel - FEMOF_19 (Multi Color, numeric_8)ASIN:  B0BRQT2ZJTSKU:  AA-PC1E-AFK2",
                "thumbnail": "https://m.media-amazon.com/images/I/31YwkleHGaL._SCLZZZZZZZ__SX55_.jpg",
                "uri": "https://www.amazon.in/gp/product/B0BRQT2ZJT",
                "transaction": {
                    "listingPrice": "₹595.00",
                    "tax": "63.75",
                    "payment": "₹466.52",
                    "shipping": "-₹84.96"
                }
            }
        ],
        "customer": {
            "name": "Sanskriti",
            "address": "NEW DELHI, DELHI",
            "pincode": "110032"
        }
    },
    {
        "id": "405-8574208-0279568",
        "uri": "https://sellercentral.amazon.in/orders-v3/order/405-8574208-0279568",
        "order": "Tue, 7 Mar, 2023, 2:40 pm IST",
        "shipment": "Wed, 8 Mar, 2023",
        "delivery": "Thu, 9 Mar, 2023",
        "status": "Delivered to buyer",
        "products": [
            {
                "name": "Angel Sales Women's Eva Comfortable Wedges Chappal Sliper (Grey); Size: 9 - FEMOF_04ASIN:  B0BR7QNJ8BSKU:  FEMOF_004-GY/9",
                "thumbnail": "https://m.media-amazon.com/images/I/31M5uBtFTBL._SCLZZZZZZZ__SX55_.jpg",
                "uri": "https://www.amazon.in/gp/product/B0BR7QNJ8B",
                "transaction": {
                    "listingPrice": "₹655.00",
                    "tax": "70.18",
                    "payment": "₹396.37",
                    "shipping": "-₹594.05"
                }
            }
        ],
        "customer": {
            "name": "Rahul",
            "address": "PIMPRI CHINCHWAD, MAHARASHTRA",
            "pincode": "411033"
        }
    },
    {
        "id": "407-8126647-9603503",
        "uri": "https://sellercentral.amazon.in/orders-v3/order/407-8126647-9603503",
        "order": "Thu, 9 Mar, 2023, 1:32 am IST",
        "shipment": "Thu, 9 Mar, 2023",
        "delivery": "Sun, 12 Mar, 2023",
        "status": "Delivered to buyer",
        "products": [
            {
                "name": "Angel Sales Womens Stylish Heels (Golden, numeric_6)ASIN:  B0BSDFZJL6SKU:  C7-KKCB-4ZOF",
                "thumbnail": "https://m.media-amazon.com/images/I/31cUxy8udGL._SCLZZZZZZZ__SX55_.jpg",
                "uri": "https://www.amazon.in/gp/product/B0BSDFZJL6",
                "transaction": {
                    "listingPrice": "₹729.00",
                    "tax": "78.11",
                    "payment": "₹566.66",
                    "shipping": "-₹84.96"
                }
            }
        ],
        "customer": {
            "name": "Dr",
            "address": "BENGALURU, KARNATAKA",
            "pincode": "560074"
        }
    },
    {
        "id": "171-8620244-4258755",
        "uri": "https://sellercentral.amazon.in/orders-v3/order/171-8620244-4258755",
        "order": "Thu, 9 Mar, 2023, 11:17 am IST",
        "shipment": "Thu, 9 Mar, 2023",
        "delivery": "Sun, 12 Mar, 2023",
        "status": "Delivered to buyer",
        "products": [
            {
                "name": "Angel Sales Women Tranparent Bow Design Flat Chappal (White, Numeric_8)ASIN:  B0BSMC277SSKU:  5R-A9EM-JLVY",
                "thumbnail": "https://m.media-amazon.com/images/I/31lk5wsrZHL._SCLZZZZZZZ__SX55_.jpg",
                "uri": "https://www.amazon.in/gp/product/B0BSMC277S",
                "transaction": {
                    "listingPrice": "₹653.00",
                    "tax": "69.96",
                    "payment": "₹503.89",
                    "shipping": "-₹84.96"
                }
            }
        ],
        "customer": {
            "name": "Asha",
            "address": "BANGALORE, KARNATAKA",
            "pincode": "560098"
        }
    },
    {
        "id": "171-9301650-6058752",
        "uri": "https://sellercentral.amazon.in/orders-v3/order/171-9301650-6058752",
        "order": "Thu, 9 Mar, 2023, 11:43 am IST",
        "shipment": "Thu, 9 Mar, 2023",
        "delivery": "Mon, 13 Mar, 2023",
        "status": "Delivered to buyer",
        "products": [
            {
                "name": "Angel Sales Women's Multi Color Bow Wedge Heel - FEMOF_19 (Multi Color, numeric_5)ASIN:  B0BRQRCGB8SKU:  MS-GG5E-KZ1Y",
                "thumbnail": "https://m.media-amazon.com/images/I/31YwkleHGaL._SCLZZZZZZZ__SX55_.jpg",
                "uri": "https://www.amazon.in/gp/product/B0BRQRCGB8",
                "transaction": {
                    "listingPrice": "₹595.00",
                    "tax": "63.75",
                    "payment": "₹466.52",
                    "shipping": "-₹84.96"
                }
            }
        ],
        "customer": {
            "name": "Healthmedic",
            "address": "LUCKNOW, UTTAR PRADESH",
            "pincode": "226010"
        }
    },
    {
        "id": "171-6241140-5709958",
        "uri": "https://sellercentral.amazon.in/orders-v3/order/171-6241140-5709958",
        "order": "Thu, 9 Mar, 2023, 8:05 pm IST",
        "shipment": "Fri, 10 Mar, 2023",
        "delivery": "Tue, 14 Mar, 2023",
        "status": "Delivered to buyer",
        "products": [
            {
                "name": "Angel Sales Women's Flower Wedge Heel - FEMOF_20 (Peach, numeric_6)ASIN:  B0BRQW7F8WSKU:  FY-YNOF-QH9T",
                "thumbnail": "https://m.media-amazon.com/images/I/31DHOht3G7L._SCLZZZZZZZ__SX55_.jpg",
                "uri": "https://www.amazon.in/gp/product/B0BRQW7F8W",
                "transaction": {
                    "listingPrice": "₹499.00",
                    "tax": "53.46",
                    "payment": "₹427.39",
                    "shipping": "-₹84.96"
                }
            }
        ],
        "customer": {
            "name": "Ajay",
            "address": "TIRUPPUR, TAMIL NADU",
            "pincode": "641604"
        }
    },
    {
        "id": "407-6317871-0008308",
        "uri": "https://sellercentral.amazon.in/orders-v3/order/407-6317871-0008308",
        "order": "Thu, 9 Mar, 2023, 11:34 pm IST",
        "shipment": "Fri, 10 Mar, 2023",
        "delivery": "Tue, 14 Mar, 2023",
        "status": "Delivered to buyer",
        "products": [
            {
                "name": "Angel Sales Women's & Girl's Party Ethnic Block Heels Mules Sandal(EW-001) (Golden, numeric_7)ASIN:  B0BTJ8BPZTSKU:  AN-80JD-HI8Y",
                "thumbnail": "https://m.media-amazon.com/images/I/31WKQVaJHtL._SCLZZZZZZZ__SX55_.jpg",
                "uri": "https://www.amazon.in/gp/product/B0BTJ8BPZT",
                "transaction": {
                    "listingPrice": "₹815.00",
                    "tax": "87.32",
                    "refund": "-₹740.60",
                    "payment": "₹652.10",
                    "shipping": "-₹84.96"
                }
            }
        ],
        "customer": {
            "name": "Shamla",
            "address": "KOZHIKODE, KERALA",
            "pincode": "673032"
        }
    },
    {
        "id": "171-4311384-4061914",
        "uri": "https://sellercentral.amazon.in/orders-v3/order/171-4311384-4061914",
        "order": "Fri, 10 Mar, 2023, 5:31 pm IST",
        "shipment": "Sat, 11 Mar, 2023",
        "delivery": "Tue, 14 Mar, 2023",
        "status": "Delivered to buyer",
        "products": [
            {
                "name": "Angel Sales Women Tranparent Bow Design Flat Chappal (White, Numeric_5)ASIN:  B0BSMMBX7QSKU:  XR-YCCP-TJWB",
                "thumbnail": "https://m.media-amazon.com/images/I/31laiDW3CvL._SCLZZZZZZZ__SX55_.jpg",
                "uri": "https://www.amazon.in/gp/product/B0BSMMBX7Q",
                "transaction": {
                    "listingPrice": "₹653.00",
                    "tax": "66.46",
                    "refund": "-₹565.43",
                    "payment": "₹476.93",
                    "shipping": "-₹84.96"
                }
            }
        ],
        "customer": {
            "name": "Alka",
            "address": "GURUGRAM, HARYANA",
            "pincode": "122011"
        }
    },
    {
        "id": "404-8776521-6106755",
        "uri": "https://sellercentral.amazon.in/orders-v3/order/404-8776521-6106755",
        "order": "Fri, 10 Mar, 2023, 8:34 pm IST",
        "shipment": "Sat, 11 Mar, 2023",
        "delivery": "Tue, 14 Mar, 2023",
        "status": "Delivered to buyer",
        "products": [
            {
                "name": "Angel Sales Women's Traditional Ethnic Flat Designer Mules (Golden, Numeric_7)ASIN:  B0BSDHSTY1SKU:  VJ-CXSA-EB1K",
                "thumbnail": "https://m.media-amazon.com/images/I/31rd-HGosxL._SCLZZZZZZZ__SX55_.jpg",
                "uri": "https://www.amazon.in/gp/product/B0BSDHSTY1",
                "transaction": {
                    "listingPrice": "₹545.00",
                    "tax": "55.47",
                    "refund": "-₹480.69",
                    "payment": "₹392.19",
                    "shipping": "-₹84.96"
                }
            }
        ],
        "customer": {
            "name": "ANU",
            "address": "BENGALURU, K",
            "pincode": "560067"
        }
    },
    {
        "id": "403-7730774-3019501",
        "uri": "https://sellercentral.amazon.in/orders-v3/order/403-7730774-3019501",
        "order": "Fri, 10 Mar, 2023, 9:25 pm IST",
        "shipment": "Sat, 11 Mar, 2023",
        "delivery": "Sun, 12 Mar, 2023",
        "status": "Delivered to buyer",
        "products": [
            {
                "name": "Angel Sales Womens Flat Mirror (White, numeric_8)ASIN:  B0BSDFC1YRSKU:  M0-CT7Q-9XBD",
                "thumbnail": "https://m.media-amazon.com/images/I/31uxQw1OsIL._SCLZZZZZZZ__SX55_.jpg",
                "uri": "https://www.amazon.in/gp/product/B0BSDFC1YR",
                "transaction": {
                    "listingPrice": "₹599.00",
                    "tax": "64.18",
                    "payment": "₹459.31",
                    "shipping": "-₹47.20"
                }
            }
        ],
        "customer": {
            "name": "Ami",
            "address": "Mumbai, MAHARASHTRA",
            "pincode": "400080"
        }
    },
    {
        "id": "406-4525075-4799525",
        "uri": "https://sellercentral.amazon.in/orders-v3/order/406-4525075-4799525",
        "order": "Sat, 11 Mar, 2023, 9:26 am IST",
        "shipment": "Sat, 11 Mar, 2023",
        "delivery": "Wed, 15 Mar, 2023",
        "status": "Delivered to buyer",
        "products": [
            {
                "name": "Angel Sales Women's Eva Comfortable Wedges Chappal Sliper (Grey); Size: 7 - FEMOF_04ASIN:  B0BR7PQ3BJSKU:  FEMOF_004-GY/7",
                "thumbnail": "https://m.media-amazon.com/images/I/31M5uBtFTBL._SCLZZZZZZZ__SX55_.jpg",
                "uri": "https://www.amazon.in/gp/product/B0BR7PQ3BJ",
                "transaction": {
                    "listingPrice": "₹655.00",
                    "tax": "66.67",
                    "refund": "-₹566.99",
                    "payment": "₹478.49",
                    "shipping": "-₹80.24"
                }
            }
        ],
        "customer": {
            "name": "Archana",
            "address": "GONDAL, GUJARAT",
            "pincode": "360311"
        }
    },
    {
        "id": "402-6393155-9166750",
        "uri": "https://sellercentral.amazon.in/orders-v3/order/402-6393155-9166750",
        "order": "Sat, 11 Mar, 2023, 4:55 pm IST",
        "shipment": "Sun, 12 Mar, 2023",
        "delivery": "Sun, 19 Mar, 2023",
        "status": "Delivered to buyer",
        "products": [
            {
                "name": "Angel Sales Women's Multi Color Bow Wedge Heel - FEMOF_19 (Multi Color, numeric_5)ASIN:  B0BRQRCGB8SKU:  MS-GG5E-KZ1Y",
                "thumbnail": "https://m.media-amazon.com/images/I/31YwkleHGaL._SCLZZZZZZZ__SX55_.jpg",
                "uri": "https://www.amazon.in/gp/product/B0BRQRCGB8",
                "transaction": {
                    "listingPrice": "₹595.00",
                    "tax": "63.75",
                    "payment": "₹466.52",
                    "shipping": "-₹84.96"
                }
            }
        ],
        "customer": {
            "name": "Rimly",
            "address": "GUWAHATI, ASSAM",
            "pincode": "781037"
        }
    },
    {
        "id": "408-1153041-4554715",
        "uri": "https://sellercentral.amazon.in/orders-v3/order/408-1153041-4554715",
        "order": "Sat, 11 Mar, 2023, 5:43 pm IST",
        "shipment": "Sun, 12 Mar, 2023",
        "delivery": "Fri, 17 Mar, 2023",
        "status": "Delivered to buyer",
        "products": [
            {
                "name": "Angel Sales Women's Flower Wedge Heel - FEMOF_20 (Peach, numeric_8)ASIN:  B0BRQV4BCPSKU:  QF-YSLS-XSDL",
                "thumbnail": "https://m.media-amazon.com/images/I/31DHOht3G7L._SCLZZZZZZZ__SX55_.jpg",
                "uri": "https://www.amazon.in/gp/product/B0BRQV4BCP",
                "transaction": {
                    "listingPrice": "₹499.00",
                    "tax": "50.79",
                    "refund": "-₹405.32",
                    "payment": "₹405.32",
                    "shipping": "-₹84.96"
                }
            }
        ],
        "customer": {
            "name": "sheeba",
            "address": "pathanamthitta, KERALA",
            "pincode": "689645"
        }
    },
    {
        "id": "406-7031205-7517146",
        "uri": "https://sellercentral.amazon.in/orders-v3/order/406-7031205-7517146",
        "order": "Sun, 12 Mar, 2023, 12:16 pm IST",
        "shipment": "Sun, 12 Mar, 2023",
        "delivery": "Fri, 17 Mar, 2023",
        "status": "Delivered to buyer",
        "products": [
            {
                "name": "Angel Sales Women's Multi Color Bow Wedge Heel - FEMOF_19 (Multi Color, numeric_5)ASIN:  B0BRQRCGB8SKU:  MS-GG5E-KZ1Y",
                "thumbnail": "https://m.media-amazon.com/images/I/31YwkleHGaL._SCLZZZZZZZ__SX55_.jpg",
                "uri": "https://www.amazon.in/gp/product/B0BRQRCGB8",
                "transaction": {
                    "listingPrice": "₹595.00",
                    "tax": "63.75",
                    "payment": "₹466.52",
                    "shipping": "-₹84.96"
                }
            }
        ],
        "customer": {
            "name": "Priyanka",
            "address": "MARALIA, JAMMU & KASHMIR",
            "pincode": "181101"
        }
    },
    {
        "id": "405-3285031-3942751",
        "uri": "https://sellercentral.amazon.in/orders-v3/order/405-3285031-3942751",
        "order": "Sun, 12 Mar, 2023, 8:28 pm IST",
        "shipment": "Mon, 13 Mar, 2023",
        "delivery": "Fri, 17 Mar, 2023",
        "status": "Delivered to buyer",
        "products": [
            {
                "name": "Angel Sales Women's Multi Color Bow Wedge Heel - FEMOF_19 (Multi Color, numeric_5)ASIN:  B0BRQRCGB8SKU:  MS-GG5E-KZ1Y",
                "thumbnail": "https://m.media-amazon.com/images/I/31YwkleHGaL._SCLZZZZZZZ__SX55_.jpg",
                "uri": "https://www.amazon.in/gp/product/B0BRQRCGB8",
                "transaction": {
                    "listingPrice": "₹595.00",
                    "tax": "63.75",
                    "refund": "-₹555.02",
                    "payment": "₹466.52",
                    "shipping": "-₹84.96"
                }
            }
        ],
        "customer": {
            "name": "Serene",
            "address": "PRAYAGRAJ, UTTAR PRADESH",
            "pincode": "211001"
        }
    },
    {
        "id": "403-7580509-3741150",
        "uri": "https://sellercentral.amazon.in/orders-v3/order/403-7580509-3741150",
        "order": "Sun, 12 Mar, 2023, 11:43 pm IST",
        "shipment": "Mon, 13 Mar, 2023",
        "delivery": "Thu, 16 Mar, 2023",
        "status": "Delivered to buyer",
        "products": [
            {
                "name": "Angel Sales Women's Eva Comfortable Wedges Chappal Sliper (Grey); Size: 9 - FEMOF_04ASIN:  B0BR7QNJ8BSKU:  FEMOF_004-GY/9",
                "thumbnail": "https://m.media-amazon.com/images/I/31M5uBtFTBL._SCLZZZZZZZ__SX55_.jpg",
                "uri": "https://www.amazon.in/gp/product/B0BR7QNJ8B",
                "transaction": {
                    "listingPrice": "₹655.00",
                    "tax": "66.67",
                    "refund": "-₹566.99",
                    "payment": "₹478.49",
                    "shipping": "-₹84.96"
                }
            }
        ],
        "customer": {
            "name": "Sree",
            "address": "BENGALURU, KARNATAKA",
            "pincode": "560067"
        }
    },
    {
        "id": "406-8857935-4951563",
        "uri": "https://sellercentral.amazon.in/orders-v3/order/406-8857935-4951563",
        "order": "Mon, 13 Mar, 2023, 1:23 am IST",
        "shipment": "Mon, 13 Mar, 2023",
        "delivery": "Thu, 16 Mar, 2023",
        "status": "Delivered to buyer",
        "products": [
            {
                "name": "Angel Sales Women's Multi Color Bow Wedge Heel - FEMOF_19 (Multi Color, numeric_4)ASIN:  B0BRQRX696SKU:  MN-N5QI-9H00",
                "thumbnail": "https://m.media-amazon.com/images/I/31YwkleHGaL._SCLZZZZZZZ__SX55_.jpg",
                "uri": "https://www.amazon.in/gp/product/B0BRQRX696",
                "transaction": {
                    "listingPrice": "₹595.00",
                    "tax": "63.75",
                    "payment": "₹363.24",
                    "shipping": "-₹555.02"
                }
            }
        ],
        "customer": {
            "name": "apoorva",
            "address": "NEW DELHI, DELHI",
            "pincode": "110017"
        }
    },
    {
        "id": "406-6175339-0961127",
        "uri": "https://sellercentral.amazon.in/orders-v3/order/406-6175339-0961127",
        "order": "Tue, 14 Mar, 2023, 1:51 pm IST",
        "shipment": "Wed, 15 Mar, 2023",
        "delivery": "Sat, 18 Mar, 2023",
        "status": "Delivered to buyer",
        "products": [
            {
                "name": "Angel Sales Women's Eva Comfortable Wedges Chappal Sliper (Grey); Size: 9 - FEMOF_04ASIN:  B0BR7QNJ8BSKU:  FEMOF_004-GY/9",
                "thumbnail": "https://m.media-amazon.com/images/I/31M5uBtFTBL._SCLZZZZZZZ__SX55_.jpg",
                "uri": "https://www.amazon.in/gp/product/B0BR7QNJ8B",
                "transaction": {
                    "listingPrice": "₹655.00",
                    "tax": "70.18",
                    "refund": "-₹594.04",
                    "payment": "₹505.54",
                    "shipping": "-₹84.96"
                }
            }
        ],
        "customer": {
            "name": "BARATHRAM",
            "address": "CHENNAI, TAMIL NADU",
            "pincode": "600083"
        }
    },
    {
        "id": "405-6376687-0395530",
        "uri": "https://sellercentral.amazon.in/orders-v3/order/405-6376687-0395530",
        "order": "Tue, 14 Mar, 2023, 5:12 pm IST",
        "shipment": "Wed, 15 Mar, 2023",
        "delivery": "Mon, 20 Mar, 2023",
        "status": "Delivered to buyer",
        "products": [
            {
                "name": "Angel Sales Women's Multi Color Bow Wedge Heel - FEMOF_19 (Multi Color, numeric_5)ASIN:  B0BRQRCGB8SKU:  MS-GG5E-KZ1Y",
                "thumbnail": "https://m.media-amazon.com/images/I/31YwkleHGaL._SCLZZZZZZZ__SX55_.jpg",
                "uri": "https://www.amazon.in/gp/product/B0BRQRCGB8",
                "transaction": {
                    "listingPrice": "₹595.00",
                    "tax": "63.75",
                    "payment": "₹466.52",
                    "shipping": "-₹84.96"
                }
            }
        ],
        "customer": {
            "name": "Nirmal",
            "address": "NAGROTA BAGWAN, HIMACHAL PRADESH",
            "pincode": "176047"
        }
    },
    {
        "id": "171-3206546-9226763",
        "uri": "https://sellercentral.amazon.in/orders-v3/order/171-3206546-9226763",
        "order": "Tue, 14 Mar, 2023, 8:04 pm IST",
        "shipment": "Wed, 15 Mar, 2023",
        "delivery": "Mon, 20 Mar, 2023",
        "status": "Delivered to buyer",
        "products": [
            {
                "name": "Angel Sales Women's Multi Color Bow Wedge Heel - FEMOF_19 (Multi Color, numeric_6)ASIN:  B0BRQR3P6CSKU:  US-C5PS-D9YK",
                "thumbnail": "https://m.media-amazon.com/images/I/31YwkleHGaL._SCLZZZZZZZ__SX55_.jpg",
                "uri": "https://www.amazon.in/gp/product/B0BRQR3P6C",
                "transaction": {
                    "listingPrice": "₹595.00",
                    "tax": "63.75",
                    "payment": "₹466.52",
                    "shipping": "-₹84.96"
                }
            }
        ],
        "customer": {
            "name": "priya",
            "address": "CHAMBA, HIMACHAL PRADESH",
            "pincode": "176310"
        }
    },
    {
        "id": "171-9485063-6788312",
        "uri": "https://sellercentral.amazon.in/orders-v3/order/171-9485063-6788312",
        "order": "Tue, 14 Mar, 2023, 8:42 pm IST",
        "shipment": "Sun, 19 Mar, 2023",
        "delivery": "Tue, 21 Mar, 2023",
        "status": "Delivered to buyer",
        "products": [
            {
                "name": "Angel Sales Women's Wedge Heels Sandals (Peach, numeric_5)ASIN:  B0BX4PTP27SKU:  O0-QYQ6-DVH8",
                "thumbnail": "https://m.media-amazon.com/images/I/31bIQaWC-DL._SCLZZZZZZZ__SX55_.jpg",
                "uri": "https://www.amazon.in/gp/product/B0BX4PTP27",
                "transaction": {
                    "listingPrice": "₹599.00",
                    "tax": "64.18",
                    "refund": "-₹469.90",
                    "payment": "₹469.90",
                    "shipping": "-₹60.18"
                }
            }
        ],
        "customer": {
            "name": "Rohit",
            "address": "PUNE, MAHARASHTRA",
            "pincode": "411014"
        }
    },
    {
        "id": "407-6536688-8614734",
        "uri": "https://sellercentral.amazon.in/orders-v3/order/407-6536688-8614734",
        "order": "Wed, 15 Mar, 2023, 10:43 am IST",
        "shipment": "Wed, 15 Mar, 2023",
        "delivery": "Sun, 19 Mar, 2023",
        "status": "Delivered to buyer",
        "products": [
            {
                "name": "Angel Sales Women's & Girl's Party Ethnic Block Heels Mules Sandal(EW-001) (Cream, numeric_8)ASIN:  B0BTJ9FP5RSKU:  EZ-76TR-CVQL",
                "thumbnail": "https://m.media-amazon.com/images/I/31dPGwpVYEL._SCLZZZZZZZ__SX55_.jpg",
                "uri": "https://www.amazon.in/gp/product/B0BTJ9FP5R",
                "transaction": {
                    "listingPrice": "₹815.00",
                    "tax": "87.32",
                    "payment": "₹652.10",
                    "shipping": "-₹84.96"
                }
            }
        ],
        "customer": {
            "name": "Ameen",
            "address": "KOZHIKODE, KERALA",
            "pincode": "673017"
        }
    },
    {
        "id": "402-6263096-6434768",
        "uri": "https://sellercentral.amazon.in/orders-v3/order/402-6263096-6434768",
        "order": "Wed, 15 Mar, 2023, 4:21 pm IST",
        "shipment": "Thu, 16 Mar, 2023",
        "delivery": "Tue, 21 Mar, 2023",
        "status": "Delivered to buyer",
        "products": [
            {
                "name": "Angel Sales Women's Multi Color Bow Wedge Heel - FEMOF_19 (Multi Color, numeric_8)ASIN:  B0BRQT2ZJTSKU:  AA-PC1E-AFK2",
                "thumbnail": "https://m.media-amazon.com/images/I/31YwkleHGaL._SCLZZZZZZZ__SX55_.jpg",
                "uri": "https://www.amazon.in/gp/product/B0BRQT2ZJT",
                "transaction": {
                    "listingPrice": "₹595.00",
                    "tax": "63.75",
                    "payment": "₹466.52",
                    "shipping": "-₹84.96"
                }
            }
        ],
        "customer": {
            "name": "Preeti",
            "address": "LUCKNOW, UTTAR PRADESH",
            "pincode": "226303"
        }
    },
    {
        "id": "171-7824753-4705942",
        "uri": "https://sellercentral.amazon.in/orders-v3/order/171-7824753-4705942",
        "order": "Thu, 16 Mar, 2023, 9:00 pm IST",
        "shipment": "Fri, 17 Mar, 2023",
        "delivery": "Tue, 21 Mar, 2023",
        "status": "Delivered to buyer",
        "products": [
            {
                "name": "Angel Sales Women's Multi Color Bow Wedge Heel - FEMOF_19 (Multi Color, numeric_5)ASIN:  B0BRQRCGB8SKU:  MS-GG5E-KZ1Y",
                "thumbnail": "https://m.media-amazon.com/images/I/31YwkleHGaL._SCLZZZZZZZ__SX55_.jpg",
                "uri": "https://www.amazon.in/gp/product/B0BRQRCGB8",
                "transaction": {
                    "listingPrice": "₹595.00",
                    "tax": "63.75",
                    "refund": "-₹555.02",
                    "payment": "₹466.52",
                    "shipping": "-₹84.96"
                }
            }
        ],
        "customer": {
            "name": "Passina",
            "address": "COIMBATORE, TAMIL NADU",
            "pincode": "641042"
        }
    },
    {
        "id": "404-3877752-5488369",
        "uri": "https://sellercentral.amazon.in/orders-v3/order/404-3877752-5488369",
        "order": "Fri, 17 Mar, 2023, 1:11 pm IST",
        "shipment": "Sat, 18 Mar, 2023",
        "delivery": "Wed, 22 Mar, 2023",
        "status": "Delivered to buyer",
        "products": [
            {
                "name": "Angel Sales Women's Multi Color Bow Wedge Heel - FEMOF_19 (Multi Color, numeric_7)ASIN:  B0BRQR5TTNSKU:  F2-NH7X-512M",
                "thumbnail": "https://m.media-amazon.com/images/I/31YwkleHGaL._SCLZZZZZZZ__SX55_.jpg",
                "uri": "https://www.amazon.in/gp/product/B0BRQR5TTN",
                "transaction": {
                    "listingPrice": "₹595.00",
                    "tax": "63.75",
                    "payment": "₹466.52",
                    "shipping": "-₹84.96"
                }
            }
        ],
        "customer": {
            "name": "RAJNEE",
            "address": "KOTA, RAJASTHAN",
            "pincode": "324006"
        }
    },
    {
        "id": "406-4570307-0893949",
        "uri": "https://sellercentral.amazon.in/orders-v3/order/406-4570307-0893949",
        "order": "Sat, 18 Mar, 2023, 8:42 am IST",
        "shipment": "Sat, 18 Mar, 2023",
        "delivery": "Mon, 27 Mar, 2023",
        "status": "Delivered to buyer",
        "products": [
            {
                "name": "Angel Sales Women's Multi Color Bow Wedge Heel - FEMOF_19 (Multi Color, numeric_6)ASIN:  B0BRQR3P6CSKU:  US-C5PS-D9YK",
                "thumbnail": "https://m.media-amazon.com/images/I/31YwkleHGaL._SCLZZZZZZZ__SX55_.jpg",
                "uri": "https://www.amazon.in/gp/product/B0BRQR3P6C",
                "transaction": {
                    "listingPrice": "₹595.00",
                    "tax": "63.75",
                    "payment": "₹466.52",
                    "shipping": "-₹84.96"
                }
            }
        ],
        "customer": {
            "name": "Yoowanira",
            "address": "JOWAI, MEGHALAYA",
            "pincode": "793150"
        }
    },
    {
        "id": "402-9347726-1071522",
        "uri": "https://sellercentral.amazon.in/orders-v3/order/402-9347726-1071522",
        "order": "Sun, 19 Mar, 2023, 3:48 pm IST",
        "shipment": "Mon, 20 Mar, 2023",
        "delivery": "Tue, 21 Mar, 2023",
        "status": "Delivered to buyer",
        "products": [
            {
                "name": "Angel Sales Women's Eva Comfortable Sandal (Black); Size: 8 - FEMOF_05ASIN:  B0BR7S521BSKU:  FEMOF_005-BK/8",
                "thumbnail": "https://m.media-amazon.com/images/I/31eEqRABkLL._SCLZZZZZZZ__SX55_.jpg",
                "uri": "https://www.amazon.in/gp/product/B0BR7S521B",
                "transaction": {
                    "listingPrice": "₹465.00",
                    "tax": "47.33",
                    "refund": "-₹435.73",
                    "payment": "₹376.73",
                    "shipping": "-₹47.20"
                }
            }
        ],
        "customer": {
            "name": "Sneha",
            "address": "kalyan, MAHARASHTRA",
            "pincode": "421306"
        }
    },
    {
        "id": "403-8972323-3999550",
        "uri": "https://sellercentral.amazon.in/orders-v3/order/403-8972323-3999550",
        "order": "Sun, 19 Mar, 2023, 7:10 pm IST",
        "shipment": "Mon, 20 Mar, 2023",
        "delivery": "Tue, 21 Mar, 2023",
        "status": "Delivered to buyer",
        "products": [
            {
                "name": "Angel Sales Women's Comfortable Wedge Heel(CB) (Golden, numeric_7)ASIN:  B0BTK7RL89SKU:  FJ-DDX7-OC44",
                "thumbnail": "https://m.media-amazon.com/images/I/31zrM44YhvL._SCLZZZZZZZ__SX55_.jpg",
                "uri": "https://www.amazon.in/gp/product/B0BTK7RL89",
                "transaction": {
                    "listingPrice": "₹699.00",
                    "tax": "74.90",
                    "payment": "₹554.25",
                    "shipping": "-₹47.20"
                }
            }
        ],
        "customer": {
            "name": "sapna",
            "address": "MUMBAI, MAHARASHTRA",
            "pincode": "400067"
        }
    },
    {
        "id": "408-5082481-8810769",
        "uri": "https://sellercentral.amazon.in/orders-v3/order/408-5082481-8810769",
        "order": "Sun, 19 Mar, 2023, 11:53 pm IST",
        "shipment": "Mon, 20 Mar, 2023",
        "delivery": "Fri, 24 Mar, 2023",
        "status": "Delivered to buyer",
        "products": [
            {
                "name": "Angel Sales Womens Wedges Sandal 2.5 Inch Heel (Peach, numeric_7)ASIN:  B0BV81RW3DSKU:  RF-2AYL-ZNNX",
                "thumbnail": "https://m.media-amazon.com/images/I/311s5VeqbML._SCLZZZZZZZ__SX55_.jpg",
                "uri": "https://www.amazon.in/gp/product/B0BV81RW3D",
                "transaction": {
                    "listingPrice": "₹597.00",
                    "tax": "60.76",
                    "payment": "₹443.04",
                    "shipping": "-₹84.96"
                }
            }
        ],
        "customer": {
            "name": "Maya",
            "address": "THIRUVANANTHAPURAM, KERALA",
            "pincode": "695005"
        }
    },
    {
        "id": "408-2903591-3757117",
        "uri": "https://sellercentral.amazon.in/orders-v3/order/408-2903591-3757117",
        "order": "Mon, 20 Mar, 2023, 8:31 am IST",
        "shipment": "Mon, 20 Mar, 2023",
        "delivery": "Fri, 24 Mar, 2023",
        "status": "Delivered to buyer",
        "products": [
            {
                "name": "Angel Sales Women's Multi Color Bow Wedge Heel - FEMOF_19 (Multi Color, numeric_5)ASIN:  B0BRQRCGB8SKU:  MS-GG5E-KZ1Y",
                "thumbnail": "https://m.media-amazon.com/images/I/31YwkleHGaL._SCLZZZZZZZ__SX55_.jpg",
                "uri": "https://www.amazon.in/gp/product/B0BRQRCGB8",
                "transaction": {
                    "listingPrice": "₹595.00",
                    "tax": "63.75",
                    "payment": "-₹363.24",
                    "shipping": "₹363.24"
                }
            }
        ],
        "customer": {
            "name": "Neha",
            "address": "SHAHKOT, PUNJAB",
            "pincode": "144702"
        }
    },
    {
        "id": "402-7090419-7164333",
        "uri": "https://sellercentral.amazon.in/orders-v3/order/402-7090419-7164333",
        "order": "Mon, 20 Mar, 2023, 1:42 pm IST",
        "shipment": "Tue, 21 Mar, 2023",
        "delivery": "Wed, 22 Mar, 2023",
        "status": "Delivered to buyer",
        "products": [
            {
                "name": "Angel Sales Women's & Girl's Party Ethnic Block Heels Mules Sandal(EW-001) (Peach, numeric_8)ASIN:  B0BTJ7DWBQSKU:  GW-LPEF-NVDI",
                "thumbnail": "https://m.media-amazon.com/images/I/31sXRNlXa+L._SCLZZZZZZZ__SX55_.jpg",
                "uri": "https://www.amazon.in/gp/product/B0BTJ7DWBQ",
                "transaction": {
                    "listingPrice": "₹815.00",
                    "tax": "82.95",
                    "refund": "-₹706.23",
                    "payment": "₹617.73",
                    "shipping": "-₹47.20"
                }
            }
        ],
        "customer": {
            "name": "Aanchal",
            "address": "MUMBAI, MAHARASHTRA",
            "pincode": "400072"
        }
    },
    {
        "id": "407-5494899-7102740",
        "uri": "https://sellercentral.amazon.in/orders-v3/order/407-5494899-7102740",
        "order": "Mon, 20 Mar, 2023, 3:18 pm IST",
        "shipment": "Tue, 21 Mar, 2023",
        "delivery": "Sat, 25 Mar, 2023",
        "status": "Delivered to buyer",
        "products": [
            {
                "name": "Angel Sales Women's Multi Color Bow Wedge Heel - FEMOF_19 (Multi Color, numeric_5)ASIN:  B0BRQRCGB8SKU:  MS-GG5E-KZ1Y",
                "thumbnail": "https://m.media-amazon.com/images/I/31YwkleHGaL._SCLZZZZZZZ__SX55_.jpg",
                "uri": "https://www.amazon.in/gp/product/B0BRQRCGB8",
                "transaction": {
                    "listingPrice": "₹595.00",
                    "tax": "63.75",
                    "refund": "-₹555.02",
                    "payment": "₹466.52",
                    "shipping": "-₹84.96"
                }
            }
        ],
        "customer": {
            "name": "Amarjit",
            "address": "LUDHIANA, PUNJAB",
            "pincode": "141006"
        }
    },
    {
        "id": "408-4656024-7967524",
        "uri": "https://sellercentral.amazon.in/orders-v3/order/408-4656024-7967524",
        "order": "Mon, 20 Mar, 2023, 6:52 pm IST",
        "shipment": "Tue, 21 Mar, 2023",
        "delivery": "Fri, 24 Mar, 2023",
        "status": "Delivered to buyer",
        "products": [
            {
                "name": "Angel Sales Latest Open Shoes and Mules for Women's (Black, Numeric_7)ASIN:  B0BTMVNFDMSKU:  8P-M2T3-NQN4",
                "thumbnail": "https://m.media-amazon.com/images/I/317yq95hXhL._SCLZZZZZZZ__SX55_.jpg",
                "uri": "https://www.amazon.in/gp/product/B0BTMVNFDM",
                "transaction": {
                    "listingPrice": "₹539.00",
                    "tax": "57.75",
                    "payment": "-₹311.97",
                    "shipping": "₹311.97"
                }
            }
        ],
        "customer": {
            "name": "Koka",
            "address": "TIRUPATI, ANDHRA PRADESH",
            "pincode": "517502"
        }
    },
    {
        "id": "171-9437916-3265154",
        "uri": "https://sellercentral.amazon.in/orders-v3/order/171-9437916-3265154",
        "order": "Tue, 21 Mar, 2023, 8:46 am IST",
        "shipment": "Thu, 23 Mar, 2023",
        "delivery": "Mon, 27 Mar, 2023",
        "status": "Delivered to buyer",
        "products": [
            {
                "name": "Angel Sales Women's Traditional Ethnic Flat Designer Mules (Golden, Numeric_5)ASIN:  B0BSDHNKHWSKU:  WM-TTXX-IDBC",
                "thumbnail": "https://m.media-amazon.com/images/I/31rd-HGosxL._SCLZZZZZZZ__SX55_.jpg",
                "uri": "https://www.amazon.in/gp/product/B0BSDHNKHW",
                "transaction": {
                    "listingPrice": "₹545.00",
                    "tax": "55.47",
                    "payment": "₹296.50",
                    "shipping": "-₹392.19"
                }
            }
        ],
        "customer": {
            "name": "Bhavika",
            "address": "JODHPUR, RAJASTHAN",
            "pincode": "342011"
        }
    },
    {
        "id": "403-0461489-2716363",
        "uri": "https://sellercentral.amazon.in/orders-v3/order/403-0461489-2716363",
        "order": "Tue, 21 Mar, 2023, 3:15 pm IST",
        "shipment": "Thu, 23 Mar, 2023",
        "delivery": "Fri, 24 Mar, 2023",
        "status": "Delivered to buyer",
        "products": [
            {
                "name": "Angel Sales Women's Traditional Ethnic Flat Mojari Jutti (Tan, Numeric_6)ASIN:  B0BS9KNVW4SKU:  Mojari/TN-6",
                "thumbnail": "https://m.media-amazon.com/images/I/41gKqKBvKFL._SCLZZZZZZZ__SX55_.jpg",
                "uri": "https://www.amazon.in/gp/product/B0BS9KNVW4",
                "transaction": {
                    "listingPrice": "₹545.00",
                    "tax": "58.40",
                    "payment": "₹414.71",
                    "shipping": "-₹47.20"
                }
            }
        ],
        "customer": {
            "name": "Abhishek",
            "address": "NAVI MUMBAI, MAHARASHTRA",
            "pincode": "410210"
        }
    },
    {
        "id": "171-6519344-1612344",
        "uri": "https://sellercentral.amazon.in/orders-v3/order/171-6519344-1612344",
        "order": "Wed, 22 Mar, 2023, 7:06 pm IST",
        "shipment": "Thu, 23 Mar, 2023",
        "delivery": "Wed, 29 Mar, 2023",
        "status": "Delivered to buyer",
        "products": [
            {
                "name": "Angel Sales Women's Wedge Heels Sandals (Peach, numeric_5)ASIN:  B0BX4PTP27SKU:  O0-QYQ6-DVH8",
                "thumbnail": "https://m.media-amazon.com/images/I/31bIQaWC-DL._SCLZZZZZZZ__SX55_.jpg",
                "uri": "https://www.amazon.in/gp/product/B0BX4PTP27",
                "transaction": {
                    "listingPrice": "₹599.00",
                    "tax": "64.18",
                    "refund": "-₹558.39",
                    "payment": "₹469.89",
                    "shipping": "-₹84.96"
                }
            }
        ],
        "customer": {
            "name": "Tulshi&Geeta",
            "address": "RANCHI, JHARKHAND",
            "pincode": "834002"
        }
    },
    {
        "id": "171-6255758-9810713",
        "uri": "https://sellercentral.amazon.in/orders-v3/order/171-6255758-9810713",
        "order": "Thu, 23 Mar, 2023, 12:13 pm IST",
        "shipment": "Fri, 24 Mar, 2023",
        "delivery": "Tue, 28 Mar, 2023",
        "status": "Delivered to buyer",
        "products": [
            {
                "name": "Angel Sales Women's Multi Color Bow Wedge Heel - FEMOF_19 (Multi Color, numeric_4)ASIN:  B0BRQRX696SKU:  MN-N5QI-9H00",
                "thumbnail": "https://m.media-amazon.com/images/I/31YwkleHGaL._SCLZZZZZZZ__SX55_.jpg",
                "uri": "https://www.amazon.in/gp/product/B0BRQRX696",
                "transaction": {
                    "listingPrice": "₹595.00",
                    "tax": "63.75",
                    "refund": "-₹466.52",
                    "payment": "₹466.52",
                    "shipping": "-₹84.96"
                }
            }
        ],
        "customer": {
            "name": "Surovita",
            "address": "HYDERABAD, TELANGANA",
            "pincode": "500089"
        }
    },
    {
        "id": "405-2547266-5557161",
        "uri": "https://sellercentral.amazon.in/orders-v3/order/405-2547266-5557161",
        "order": "Thu, 23 Mar, 2023, 12:40 pm IST",
        "shipment": "Thu, 23 Mar, 2023",
        "delivery": "Thu, 30 Mar, 2023",
        "status": "Delivered to buyer",
        "products": [
            {
                "name": "Angel Sales Women's & Girl's Party Ethnic Block Heels Mules Sandal(EW-001) (Cream, numeric_5)ASIN:  B0BTJ6ZT7NSKU:  MH-BTR3-V6Y5",
                "thumbnail": "https://m.media-amazon.com/images/I/31dPGwpVYEL._SCLZZZZZZZ__SX55_.jpg",
                "uri": "https://www.amazon.in/gp/product/B0BTJ6ZT7N",
                "transaction": {
                    "listingPrice": "₹815.00",
                    "tax": "87.32",
                    "payment": "₹652.10",
                    "shipping": "-₹84.96"
                }
            }
        ],
        "customer": {
            "name": "Sultana",
            "address": "DARBHANGA, BIHAR",
            "pincode": "846004"
        }
    },
    {
        "id": "407-9181235-3484369",
        "uri": "https://sellercentral.amazon.in/orders-v3/order/407-9181235-3484369",
        "order": "Fri, 24 Mar, 2023, 12:25 am IST",
        "shipment": "Fri, 24 Mar, 2023",
        "delivery": "Wed, 29 Mar, 2023",
        "status": "Delivered to buyer",
        "products": [
            {
                "name": "Angel Sales Women's Multi Color Bow Wedge Heel - FEMOF_19 (Multi Color, numeric_4)ASIN:  B0BRQRX696SKU:  MN-N5QI-9H00",
                "thumbnail": "https://m.media-amazon.com/images/I/31YwkleHGaL._SCLZZZZZZZ__SX55_.jpg",
                "uri": "https://www.amazon.in/gp/product/B0BRQRX696",
                "transaction": {
                    "listingPrice": "₹595.00",
                    "tax": "63.75",
                    "payment": "₹466.52",
                    "shipping": "-₹84.96"
                }
            }
        ],
        "customer": {
            "name": "Boidehi",
            "address": "NEW TOWN, WEST BENGAL",
            "pincode": "700156"
        }
    },
    {
        "id": "407-0315004-6714729",
        "uri": "https://sellercentral.amazon.in/orders-v3/order/407-0315004-6714729",
        "order": "Fri, 24 Mar, 2023, 12:42 am IST",
        "shipment": "Fri, 24 Mar, 2023",
        "delivery": "Mon, 27 Mar, 2023",
        "status": "Delivered to buyer",
        "products": [
            {
                "name": "Angel Sales Women Casual Wedge Sandals (Black, numeric_5)ASIN:  B0BXHNHDDDSKU:  H2-1R89-OOEO",
                "thumbnail": "https://m.media-amazon.com/images/I/31PeOP4TdoL._SCLZZZZZZZ__SX55_.jpg",
                "uri": "https://www.amazon.in/gp/product/B0BXHNHDDD",
                "transaction": {
                    "listingPrice": "₹635.00",
                    "tax": "64.64",
                    "payment": "₹473.48",
                    "shipping": "-₹84.96"
                }
            }
        ],
        "customer": {
            "name": "Taranum",
            "address": "BENGALURU, KARNATAKA",
            "pincode": "560077"
        }
    },
    {
        "id": "171-2522964-0166721",
        "uri": "https://sellercentral.amazon.in/orders-v3/order/171-2522964-0166721",
        "order": "Fri, 24 Mar, 2023, 1:14 pm IST",
        "shipment": "Sat, 25 Mar, 2023",
        "delivery": "Tue, 28 Mar, 2023",
        "status": "Delivered to buyer",
        "products": [
            {
                "name": "Angel Sales Women's Multi Color Bow Wedge Heel - FEMOF_19 (Multi Color, numeric_8)ASIN:  B0BRQT2ZJTSKU:  AA-PC1E-AFK2",
                "thumbnail": "https://m.media-amazon.com/images/I/31YwkleHGaL._SCLZZZZZZZ__SX55_.jpg",
                "uri": "https://www.amazon.in/gp/product/B0BRQT2ZJT",
                "transaction": {
                    "listingPrice": "₹595.00",
                    "tax": "63.75",
                    "payment": "₹466.52",
                    "shipping": "-₹84.96"
                }
            }
        ],
        "customer": {
            "name": "Sukanksha",
            "address": "BENGALURU, KARNATAKA",
            "pincode": "560093"
        }
    },
    {
        "id": "402-6496556-1683507",
        "uri": "https://sellercentral.amazon.in/orders-v3/order/402-6496556-1683507",
        "order": "Fri, 24 Mar, 2023, 4:43 pm IST",
        "shipment": "Sat, 25 Mar, 2023",
        "delivery": "Thu, 30 Mar, 2023",
        "status": "Delivered to buyer",
        "products": [
            {
                "name": "Angel Sales Women's Multi Color Bow Wedge Heel - FEMOF_19 (Multi Color, numeric_6)ASIN:  B0BRQR3P6CSKU:  US-C5PS-D9YK",
                "thumbnail": "https://m.media-amazon.com/images/I/31YwkleHGaL._SCLZZZZZZZ__SX55_.jpg",
                "uri": "https://www.amazon.in/gp/product/B0BRQR3P6C",
                "transaction": {
                    "listingPrice": "₹595.00",
                    "tax": "63.75",
                    "refund": "-₹555.02",
                    "payment": "₹466.52",
                    "shipping": "-₹84.96"
                }
            }
        ],
        "customer": {
            "name": "Neha",
            "address": "HARIDWAR, UTTARAKHAND",
            "pincode": "249401"
        }
    },
    {
        "id": "405-4831919-2703543",
        "uri": "https://sellercentral.amazon.in/orders-v3/order/405-4831919-2703543",
        "order": "Fri, 24 Mar, 2023, 11:51 pm IST",
        "shipment": "Sat, 25 Mar, 2023",
        "delivery": "Tue, 28 Mar, 2023",
        "status": "Delivered to buyer",
        "products": [
            {
                "name": "Angel Sales Women's Wedge Heels Sandals (Black, numeric_6)ASIN:  B0BX4PSR5FSKU:  TW-J6B9-JMKN",
                "thumbnail": "https://m.media-amazon.com/images/I/31xpgQ713vL._SCLZZZZZZZ__SX55_.jpg",
                "uri": "https://www.amazon.in/gp/product/B0BX4PSR5F",
                "transaction": {
                    "listingPrice": "₹599.00",
                    "tax": "64.18",
                    "payment": "₹469.89",
                    "shipping": "-₹84.96"
                }
            }
        ],
        "customer": {
            "name": "Abirami",
            "address": "CHENNAI, TAMIL NADU",
            "pincode": "600119"
        }
    },
    {
        "id": "408-2100884-3524361",
        "uri": "https://sellercentral.amazon.in/orders-v3/order/408-2100884-3524361",
        "order": "Sat, 25 Mar, 2023, 8:20 am IST",
        "shipment": "Sat, 25 Mar, 2023",
        "delivery": "Wed, 29 Mar, 2023",
        "status": "Delivered to buyer",
        "products": [
            {
                "name": "Angel Sales Women's Multi Color Bow Wedge Heel - FEMOF_19 (Multi Color, numeric_8)ASIN:  B0BRQT2ZJTSKU:  AA-PC1E-AFK2",
                "thumbnail": "https://m.media-amazon.com/images/I/31YwkleHGaL._SCLZZZZZZZ__SX55_.jpg",
                "uri": "https://www.amazon.in/gp/product/B0BRQT2ZJT",
                "transaction": {
                    "listingPrice": "0.00",
                    "payment": "₹0.00",
                    "shipping": "-₹84.96"
                }
            }
        ],
        "customer": {
            "name": "RAJNEE",
            "address": "KOTA, RAJASTHAN",
            "pincode": "324006"
        }
    },
    {
        "id": "404-9372705-9349924",
        "uri": "https://sellercentral.amazon.in/orders-v3/order/404-9372705-9349924",
        "order": "Sat, 25 Mar, 2023, 9:22 am IST",
        "shipment": "Sat, 25 Mar, 2023",
        "delivery": "Tue, 28 Mar, 2023",
        "status": "Delivered to buyer",
        "products": [
            {
                "name": "Angel Sales Women's Multi Color Bow Wedge Heel - FEMOF_19 (Multi Color, numeric_5)ASIN:  B0BRQRCGB8SKU:  MS-GG5E-KZ1Y",
                "thumbnail": "https://m.media-amazon.com/images/I/31YwkleHGaL._SCLZZZZZZZ__SX55_.jpg",
                "uri": "https://www.amazon.in/gp/product/B0BRQRCGB8",
                "transaction": {
                    "listingPrice": "₹595.00",
                    "tax": "63.75",
                    "payment": "₹466.52",
                    "shipping": "-₹60.18"
                }
            }
        ],
        "customer": {
            "name": "Harshita",
            "address": "Ahmedabad, GUJARAT",
            "pincode": "380007"
        }
    },
    {
        "id": "408-6691409-4263528",
        "uri": "https://sellercentral.amazon.in/orders-v3/order/408-6691409-4263528",
        "order": "Sat, 25 Mar, 2023, 4:01 pm IST",
        "shipment": "Sun, 26 Mar, 2023",
        "delivery": "Wed, 29 Mar, 2023",
        "status": "Delivered to buyer",
        "products": [
            {
                "name": "Angel Sales Womens Wedges Sandal 2.5 Inch Heel (Peach, numeric_6)ASIN:  B0BV8DLXMGSKU:  83-ICRD-O9T9",
                "thumbnail": "https://m.media-amazon.com/images/I/311s5VeqbML._SCLZZZZZZZ__SX55_.jpg",
                "uri": "https://www.amazon.in/gp/product/B0BV8DLXMG",
                "transaction": {
                    "listingPrice": "₹597.00",
                    "tax": "63.96",
                    "refund": "-₹556.71",
                    "payment": "₹468.21",
                    "shipping": "-₹60.18"
                }
            }
        ],
        "customer": {
            "name": "Beeta",
            "address": "AHMEDABAD, GUJARAT",
            "pincode": "380015"
        }
    },
    {
        "id": "406-9614097-6634741",
        "uri": "https://sellercentral.amazon.in/orders-v3/order/406-9614097-6634741",
        "order": "Sat, 25 Mar, 2023, 5:53 pm IST",
        "shipment": "Sun, 26 Mar, 2023",
        "delivery": "Mon, 27 Mar, 2023",
        "status": "Delivered to buyer",
        "products": [
            {
                "name": "Angel Sales Women's & Girl's Party Ethnic Block Heels Mules Sandal(EW-001) (Grey, numeric_8)ASIN:  B0BTJBPS12SKU:  MW-UF59-VRSI",
                "thumbnail": "https://m.media-amazon.com/images/I/31KpLklvIAL._SCLZZZZZZZ__SX55_.jpg",
                "uri": "https://www.amazon.in/gp/product/B0BTJBPS12",
                "transaction": {
                    "listingPrice": "₹815.00",
                    "tax": "87.32",
                    "payment": "₹652.10",
                    "shipping": "-₹47.20"
                }
            }
        ],
        "customer": {
            "name": "Manmeet",
            "address": "Mumbai, MAHARASHTRA",
            "pincode": "400103"
        }
    },
    {
        "id": "171-3637902-5823566",
        "uri": "https://sellercentral.amazon.in/orders-v3/order/171-3637902-5823566",
        "order": "Sat, 25 Mar, 2023, 8:37 pm IST",
        "shipment": "Sun, 26 Mar, 2023",
        "delivery": "Thu, 30 Mar, 2023",
        "status": "Delivered to buyer",
        "products": [
            {
                "name": "Angel Sales Women Casual Wedge Sandals (Black, numeric_8)ASIN:  B0BXHM8X75SKU:  J2-ZD1D-08A5",
                "thumbnail": "https://m.media-amazon.com/images/I/31PeOP4TdoL._SCLZZZZZZZ__SX55_.jpg",
                "uri": "https://www.amazon.in/gp/product/B0BXHM8X75",
                "transaction": {
                    "listingPrice": "₹635.00",
                    "tax": "68.04",
                    "payment": "₹500.26",
                    "shipping": "-₹84.96"
                }
            }
        ],
        "customer": {
            "name": "Amna",
            "address": "NEW DELHI, DELHI",
            "pincode": "110024"
        }
    },
    {
        "id": "404-1095002-4549139",
        "uri": "https://sellercentral.amazon.in/orders-v3/order/404-1095002-4549139",
        "order": "Sat, 25 Mar, 2023, 10:02 pm IST",
        "shipment": "Sun, 26 Mar, 2023",
        "delivery": "Mon, 3 Apr, 2023",
        "status": "Delivered to buyer",
        "products": [
            {
                "name": "Angel Sales Women's Multi Color Bow Wedge Heel - FEMOF_19 (Multi Color, numeric_5)ASIN:  B0BRQRCGB8SKU:  MS-GG5E-KZ1Y",
                "thumbnail": "https://m.media-amazon.com/images/I/31YwkleHGaL._SCLZZZZZZZ__SX55_.jpg",
                "uri": "https://www.amazon.in/gp/product/B0BRQRCGB8",
                "transaction": {
                    "listingPrice": "₹595.00",
                    "tax": "63.75",
                    "payment": "₹466.52",
                    "shipping": "-₹84.96"
                }
            }
        ],
        "customer": {
            "name": "Ngimchule",
            "address": "DIMAPUR, NAGALAND",
            "pincode": "797112"
        }
    },
    {
        "id": "408-8729726-0387513",
        "uri": "https://sellercentral.amazon.in/orders-v3/order/408-8729726-0387513",
        "order": "Sun, 26 Mar, 2023, 7:59 am IST",
        "shipment": "Sun, 26 Mar, 2023",
        "delivery": "Fri, 31 Mar, 2023",
        "status": "Delivered to buyer",
        "products": [
            {
                "name": "Angel Sales Women's Traditional Ethnic Flat Designer Mules (Chiku, Numeric_9)ASIN:  B0BSDLH1YSSKU:  HG-CVTO-S8TZ",
                "thumbnail": "https://m.media-amazon.com/images/I/31OftNNwYfL._SCLZZZZZZZ__SX55_.jpg",
                "uri": "https://www.amazon.in/gp/product/B0BSDLH1YS",
                "transaction": {
                    "listingPrice": "₹545.00",
                    "tax": "58.39",
                    "payment": "₹414.70",
                    "shipping": "-₹84.96"
                }
            }
        ],
        "customer": {
            "name": "Barsha",
            "address": "Howrah, WEST BENGAL",
            "pincode": "711302"
        }
    },
    {
        "id": "408-4277693-2895555",
        "uri": "https://sellercentral.amazon.in/orders-v3/order/408-4277693-2895555",
        "order": "Sun, 26 Mar, 2023, 9:00 pm IST",
        "shipment": "Mon, 27 Mar, 2023",
        "delivery": "Tue, 28 Mar, 2023",
        "status": "Delivered to buyer",
        "products": [
            {
                "name": "Angel Sales Women's & Girl's Party Ethnic Block Heels Mules Sandal(EW-001) (Golden, numeric_5)ASIN:  B0BTJ8WZ7LSKU:  Q8-APOT-NON6",
                "thumbnail": "https://m.media-amazon.com/images/I/31WKQVaJHtL._SCLZZZZZZZ__SX55_.jpg",
                "uri": "https://www.amazon.in/gp/product/B0BTJ8WZ7L",
                "transaction": {
                    "listingPrice": "₹815.00",
                    "tax": "82.95",
                    "payment": "₹617.74",
                    "shipping": "-₹84.96"
                }
            }
        ],
        "customer": {
            "name": "Gaurav",
            "address": "BENGALURU, KARNATAKA",
            "pincode": "560068"
        }
    },
    {
        "id": "404-5435549-2274741",
        "uri": "https://sellercentral.amazon.in/orders-v3/order/404-5435549-2274741",
        "order": "Sun, 26 Mar, 2023, 9:30 pm IST",
        "shipment": "Mon, 27 Mar, 2023",
        "delivery": "Fri, 31 Mar, 2023",
        "status": "Delivered to buyer",
        "products": [
            {
                "name": "Angel Sales Women's Wedge Heels Sandals (Peach, numeric_8)ASIN:  B0BX4RJBXFSKU:  AV-MEMS-06M0",
                "thumbnail": "https://m.media-amazon.com/images/I/31bIQaWC-DL._SCLZZZZZZZ__SX55_.jpg",
                "uri": "https://www.amazon.in/gp/product/B0BX4RJBXF",
                "transaction": {
                    "listingPrice": "₹599.00",
                    "tax": "60.97",
                    "refund": "-₹533.14",
                    "payment": "₹444.64",
                    "shipping": "-₹84.96"
                }
            }
        ],
        "customer": {
            "name": "Susanshibu",
            "address": "ERNAKULAM, KERALA",
            "pincode": "682019"
        }
    },
    {
        "id": "407-7026152-1173157",
        "uri": "https://sellercentral.amazon.in/orders-v3/order/407-7026152-1173157",
        "order": "Sun, 26 Mar, 2023, 10:26 pm IST",
        "shipment": "Mon, 27 Mar, 2023",
        "delivery": "Tue, 28 Mar, 2023",
        "status": "Delivered to buyer",
        "products": [
            {
                "name": "Angel Sales Women's Flower Wedge Heel - FEMOF_20 (Peach, numeric_6)ASIN:  B0BRQW7F8WSKU:  FY-YNOF-QH9T",
                "thumbnail": "https://m.media-amazon.com/images/I/31DHOht3G7L._SCLZZZZZZZ__SX55_.jpg",
                "uri": "https://www.amazon.in/gp/product/B0BRQW7F8W",
                "transaction": {
                    "listingPrice": "₹499.00",
                    "tax": "50.79",
                    "payment": "₹313.92",
                    "shipping": "-₹464.31"
                }
            }
        ],
        "customer": {
            "name": "Manisha",
            "address": "Thane, MAHARASHTRA",
            "pincode": "400615"
        }
    },
    {
        "id": "403-0437769-5697103",
        "uri": "https://sellercentral.amazon.in/orders-v3/order/403-0437769-5697103",
        "order": "Mon, 27 Mar, 2023, 1:00 pm IST",
        "shipment": "Tue, 28 Mar, 2023",
        "delivery": "Sat, 1 Apr, 2023",
        "status": "Delivered to buyer",
        "products": [
            {
                "name": "Angel Sales Women's Multi Color Bow Wedge Heel - FEMOF_19 (Multi Color, numeric_5)ASIN:  B0BRQRCGB8SKU:  MS-GG5E-KZ1Y",
                "thumbnail": "https://m.media-amazon.com/images/I/31YwkleHGaL._SCLZZZZZZZ__SX55_.jpg",
                "uri": "https://www.amazon.in/gp/product/B0BRQRCGB8",
                "transaction": {
                    "listingPrice": "₹595.00",
                    "tax": "63.75",
                    "refund": "-₹466.52",
                    "payment": "₹466.52",
                    "shipping": "-₹84.96"
                }
            }
        ],
        "customer": {
            "name": "Manya",
            "address": "SHAHJAHANPUR, UTTAR PRADESH",
            "pincode": "242001"
        }
    },
    {
        "id": "405-7688956-1641100",
        "uri": "https://sellercentral.amazon.in/orders-v3/order/405-7688956-1641100",
        "order": "Mon, 27 Mar, 2023, 4:37 pm IST",
        "shipment": "Tue, 28 Mar, 2023",
        "delivery": "Mon, 3 Apr, 2023",
        "status": "Delivered to buyer",
        "products": [
            {
                "name": "Angel Sales Womens Wedges Sandal 2.5 Inch Heel (Peach, numeric_4)ASIN:  B0BV8D2J43SKU:  7R-YRJ9-1C6B",
                "thumbnail": "https://m.media-amazon.com/images/I/311s5VeqbML._SCLZZZZZZZ__SX55_.jpg",
                "uri": "https://www.amazon.in/gp/product/B0BV8D2J43",
                "transaction": {
                    "listingPrice": "₹597.00",
                    "tax": "63.96",
                    "payment": "₹468.21",
                    "shipping": "-₹84.96"
                }
            }
        ],
        "customer": {
            "name": "Shubhi",
            "address": "BHIWANI, HARYANA",
            "pincode": "127021"
        }
    },
    {
        "id": "407-7365038-3221957",
        "uri": "https://sellercentral.amazon.in/orders-v3/order/407-7365038-3221957",
        "order": "Mon, 27 Mar, 2023, 4:49 pm IST",
        "shipment": "Tue, 28 Mar, 2023",
        "delivery": "Wed, 29 Mar, 2023",
        "status": "Delivered to buyer",
        "products": [
            {
                "name": "Angel Sales Women's Multi Color Bow Wedge Heel - FEMOF_19 (Multi Color, numeric_4)ASIN:  B0BRQRX696SKU:  MN-N5QI-9H00",
                "thumbnail": "https://m.media-amazon.com/images/I/31YwkleHGaL._SCLZZZZZZZ__SX55_.jpg",
                "uri": "https://www.amazon.in/gp/product/B0BRQRX696",
                "transaction": {
                    "listingPrice": "₹595.00",
                    "tax": "63.76",
                    "payment": "₹466.51",
                    "shipping": "-₹47.20"
                }
            }
        ],
        "customer": {
            "name": "Priti",
            "address": "NAVI MUMBAI, MAHARASHTRA",
            "pincode": "410210"
        }
    },
    {
        "id": "171-4003609-2541906",
        "uri": "https://sellercentral.amazon.in/orders-v3/order/171-4003609-2541906",
        "order": "Tue, 28 Mar, 2023, 7:23 am IST",
        "shipment": "Tue, 28 Mar, 2023",
        "delivery": "Sat, 1 Apr, 2023",
        "status": "Delivered to buyer",
        "products": [
            {
                "name": "Angel Sales Women's Traditional Ethnic Flat Designer Mules (Chiku, Numeric_5)ASIN:  B0BSDKT59FSKU:  KI-8K0J-JTLF",
                "thumbnail": "https://m.media-amazon.com/images/I/31OftNNwYfL._SCLZZZZZZZ__SX55_.jpg",
                "uri": "https://www.amazon.in/gp/product/B0BSDKT59F",
                "transaction": {
                    "listingPrice": "₹545.00",
                    "tax": "58.39",
                    "payment": "₹414.70",
                    "shipping": "-₹84.96"
                }
            }
        ],
        "customer": {
            "name": "Nitesh",
            "address": "HYDERABAD, TELANGANA",
            "pincode": "500018"
        }
    },
    {
        "id": "403-1596788-4617158",
        "uri": "https://sellercentral.amazon.in/orders-v3/order/403-1596788-4617158",
        "order": "Tue, 28 Mar, 2023, 3:12 pm IST",
        "shipment": "Wed, 29 Mar, 2023",
        "delivery": "Mon, 3 Apr, 2023",
        "status": "Delivered to buyer",
        "products": [
            {
                "name": "Angel Sales Women's Multi Color Bow Wedge Heel - FEMOF_19 (Multi Color, numeric_6)ASIN:  B0BRQR3P6CSKU:  US-C5PS-D9YK",
                "thumbnail": "https://m.media-amazon.com/images/I/31YwkleHGaL._SCLZZZZZZZ__SX55_.jpg",
                "uri": "https://www.amazon.in/gp/product/B0BRQR3P6C",
                "transaction": {
                    "listingPrice": "₹595.00",
                    "tax": "63.75",
                    "refund": "-₹555.02",
                    "payment": "₹466.52",
                    "shipping": "-₹84.96"
                }
            }
        ],
        "customer": {
            "name": "Hema",
            "address": "NEW DELHI, DELHI",
            "pincode": "110020"
        }
    },
    {
        "id": "404-1880163-7007527",
        "uri": "https://sellercentral.amazon.in/orders-v3/order/404-1880163-7007527",
        "order": "Wed, 29 Mar, 2023, 3:58 am IST",
        "shipment": "Wed, 29 Mar, 2023",
        "delivery": "Sat, 1 Apr, 2023",
        "status": "Delivered to buyer",
        "products": [
            {
                "name": "Angel Sales Women's Wedge Heels Sandals (Peach, numeric_5)ASIN:  B0BX4PTP27SKU:  O0-QYQ6-DVH8",
                "thumbnail": "https://m.media-amazon.com/images/I/31bIQaWC-DL._SCLZZZZZZZ__SX55_.jpg",
                "uri": "https://www.amazon.in/gp/product/B0BX4PTP27",
                "transaction": {
                    "listingPrice": "₹599.00",
                    "tax": "64.18",
                    "payment": "₹469.89",
                    "shipping": "-₹84.96"
                }
            }
        ],
        "customer": {
            "name": "Preetha",
            "address": "BENGALURU, KARNATAKA",
            "pincode": "560025"
        }
    },
    {
        "id": "171-8279139-6564311",
        "uri": "https://sellercentral.amazon.in/orders-v3/order/171-8279139-6564311",
        "order": "Wed, 29 Mar, 2023, 7:36 pm IST",
        "shipment": "Thu, 30 Mar, 2023",
        "delivery": "Thu, 6 Apr, 2023",
        "status": "Delivered to buyer",
        "products": [
            {
                "name": "Angel Sales Women's & Girl's Party Ethnic Block Heels Mules Sandal(EW-001) (Grey, numeric_6)ASIN:  B0BTJ9H6BQSKU:  BR-545Y-OOMA",
                "thumbnail": "https://m.media-amazon.com/images/I/31tFM5zyxHL._SCLZZZZZZZ__SX55_.jpg",
                "uri": "https://www.amazon.in/gp/product/B0BTJ9H6BQ",
                "transaction": {
                    "listingPrice": "₹815.00",
                    "tax": "87.32",
                    "refund": "-₹652.10",
                    "payment": "₹652.10",
                    "shipping": "-₹84.96"
                }
            }
        ],
        "customer": {
            "name": "Nilesh",
            "address": "BANKA, BIHAR",
            "pincode": "813107"
        }
    },
    {
        "id": "403-2135226-9257958",
        "uri": "https://sellercentral.amazon.in/orders-v3/order/403-2135226-9257958",
        "order": "Wed, 29 Mar, 2023, 10:10 pm IST",
        "shipment": "Thu, 30 Mar, 2023",
        "delivery": "Fri, 31 Mar, 2023",
        "status": "Delivered to buyer",
        "products": [
            {
                "name": "Angel Sales Women's & Girl's Party Ethnic Block Heels Mules Sandal(EW-001) (Cream, numeric_5)ASIN:  B0BTJ6ZT7NSKU:  MH-BTR3-V6Y5",
                "thumbnail": "https://m.media-amazon.com/images/I/31dPGwpVYEL._SCLZZZZZZZ__SX55_.jpg",
                "uri": "https://www.amazon.in/gp/product/B0BTJ6ZT7N",
                "transaction": {
                    "listingPrice": "₹815.00",
                    "tax": "82.95",
                    "refund": "-₹706.23",
                    "payment": "₹617.73",
                    "shipping": "-₹47.20"
                }
            }
        ],
        "customer": {
            "name": "Alisha",
            "address": "THANE, MAHARASHTRA",
            "pincode": "401202"
        }
    },
    {
        "id": "403-4766819-7979565",
        "uri": "https://sellercentral.amazon.in/orders-v3/order/403-4766819-7979565",
        "order": "Thu, 30 Mar, 2023, 5:12 pm IST",
        "shipment": "Fri, 31 Mar, 2023",
        "delivery": "Mon, 3 Apr, 2023",
        "status": "Delivered to buyer",
        "products": [
            {
                "name": "Angel Sales Women's Multi Color Bow Wedge Heel - FEMOF_19 (Multi Color, numeric_7)ASIN:  B0BRQR5TTNSKU:  F2-NH7X-512M",
                "thumbnail": "https://m.media-amazon.com/images/I/31YwkleHGaL._SCLZZZZZZZ__SX55_.jpg",
                "uri": "https://www.amazon.in/gp/product/B0BRQR5TTN",
                "transaction": {
                    "listingPrice": "₹595.00",
                    "tax": "63.75",
                    "payment": "₹466.52",
                    "shipping": "-₹84.96"
                }
            }
        ],
        "customer": {
            "name": "Smita",
            "address": "Bengaluru, KARNATAKA",
            "pincode": "560049"
        }
    },
    {
        "id": "408-2485845-7708341",
        "uri": "https://sellercentral.amazon.in/orders-v3/order/408-2485845-7708341",
        "order": "Fri, 31 Mar, 2023, 12:00 am IST",
        "shipment": "Fri, 31 Mar, 2023",
        "delivery": "Mon, 3 Apr, 2023",
        "status": "Delivered to buyer",
        "products": [
            {
                "name": "Angel Sales Women's Eva Comfortable Wedges Chappal Sliper (Grey); Size: 8 - FEMOF_04ASIN:  B0BR7QRKK7SKU:  FEMOF_004-GY/8",
                "thumbnail": "https://m.media-amazon.com/images/I/31M5uBtFTBL._SCLZZZZZZZ__SX55_.jpg",
                "uri": "https://www.amazon.in/gp/product/B0BR7QRKK7",
                "transaction": {
                    "listingPrice": "₹655.00",
                    "tax": "66.67",
                    "payment": "₹478.49",
                    "shipping": "-₹60.18"
                }
            }
        ],
        "customer": {
            "name": "Nilam",
            "address": "GODHRA, GUJARAT",
            "pincode": "389001"
        }
    },
    {
        "id": "406-1966383-7080350",
        "uri": "https://sellercentral.amazon.in/orders-v3/order/406-1966383-7080350",
        "order": "Fri, 31 Mar, 2023, 8:39 am IST",
        "shipment": "Sat, 1 Apr, 2023",
        "delivery": "Sat, 8 Apr, 2023",
        "status": "Delivered to buyer",
        "products": [
            {
                "name": "Angel Sales Women's Multi Color Bow Wedge Heel - FEMOF_19 (Multi Color, numeric_4)ASIN:  B0BRQRX696SKU:  MN-N5QI-9H00",
                "thumbnail": "https://m.media-amazon.com/images/I/31YwkleHGaL._SCLZZZZZZZ__SX55_.jpg",
                "uri": "https://www.amazon.in/gp/product/B0BRQRX696",
                "transaction": {
                    "listingPrice": "₹595.00",
                    "tax": "63.75",
                    "refund": "-₹555.02",
                    "payment": "₹466.52",
                    "shipping": "-₹84.96"
                }
            }
        ],
        "customer": {
            "name": "Flitiful",
            "address": "SHILLONG, MEGHALAYA",
            "pincode": "793008"
        }
    },
    {
        "id": "407-6977324-1072362",
        "uri": "https://sellercentral.amazon.in/orders-v3/order/407-6977324-1072362",
        "order": "Fri, 31 Mar, 2023, 10:34 am IST",
        "shipment": "Fri, 31 Mar, 2023",
        "delivery": "Tue, 4 Apr, 2023",
        "status": "Delivered to buyer",
        "products": [
            {
                "name": "Angel Sales Women's Multi Color Bow Wedge Heel - FEMOF_19 (Multi Color, numeric_5)ASIN:  B0BRQRCGB8SKU:  MS-GG5E-KZ1Y",
                "thumbnail": "https://m.media-amazon.com/images/I/31YwkleHGaL._SCLZZZZZZZ__SX55_.jpg",
                "uri": "https://www.amazon.in/gp/product/B0BRQRCGB8",
                "transaction": {
                    "listingPrice": "₹595.00",
                    "tax": "63.75",
                    "refund": "-₹466.52",
                    "payment": "₹466.52",
                    "shipping": "-₹84.96"
                }
            }
        ],
        "customer": {
            "name": "Ruchi",
            "address": "SHAHJAHANPUR, UTTAR PRADESH",
            "pincode": "242001"
        }
    },
    {
        "id": "403-7804315-2167513",
        "uri": "https://sellercentral.amazon.in/orders-v3/order/403-7804315-2167513",
        "order": "Fri, 31 Mar, 2023, 12:57 pm IST",
        "shipment": "Sat, 1 Apr, 2023",
        "delivery": "Fri, 7 Apr, 2023",
        "status": "Delivered to buyer",
        "products": [
            {
                "name": "Angel Sales Women's Multi Color Bow Wedge Heel - FEMOF_19 (Multi Color, numeric_4)ASIN:  B0BRQRX696SKU:  MN-N5QI-9H00",
                "thumbnail": "https://m.media-amazon.com/images/I/31YwkleHGaL._SCLZZZZZZZ__SX55_.jpg",
                "uri": "https://www.amazon.in/gp/product/B0BRQRX696",
                "transaction": {
                    "listingPrice": "₹595.00",
                    "tax": "63.75",
                    "payment": "₹466.52",
                    "shipping": "-₹84.96"
                }
            }
        ],
        "customer": {
            "name": "Narmada",
            "address": "VEDANTA JHARSUGUDA, ODISHA",
            "pincode": "768202"
        }
    },
    {
        "id": "407-6629604-5588330",
        "uri": "https://sellercentral.amazon.in/orders-v3/order/407-6629604-5588330",
        "order": "Fri, 31 Mar, 2023, 3:36 pm IST",
        "shipment": "Sat, 1 Apr, 2023",
        "delivery": "Wed, 5 Apr, 2023",
        "status": "Delivered to buyer",
        "products": [
            {
                "name": "Angel Sales Women's Wedge Heels Sandals (Black, numeric_7)ASIN:  B0BX4PRRJQSKU:  QT-41UP-4ZTK",
                "thumbnail": "https://m.media-amazon.com/images/I/31xpgQ713vL._SCLZZZZZZZ__SX55_.jpg",
                "uri": "https://www.amazon.in/gp/product/B0BX4PRRJQ",
                "transaction": {
                    "listingPrice": "₹599.00",
                    "tax": "60.97",
                    "payment": "₹444.64",
                    "shipping": "-₹84.96"
                }
            }
        ],
        "customer": {
            "name": "Monish",
            "address": "CHENNAI, TAMIL NADU",
            "pincode": "600096"
        }
    }
]